hifive/__init__.py
hifive/fend.py
hifive/fivec.py
hifive/fivec_binning.py
hifive/fivec_data.py
hifive/fragment.py
hifive/hic.py
hifive/hic_binning.py
hifive/hic_data.py
hifive/hic_domains.py
hifive/plotting.py
hifive/quasar.py
hifive/schic.py
hifive/version.py
hifive/commands/__init__.py
hifive/commands/combine_fivec_replicates.py
hifive/commands/combine_hic_replicates.py
hifive/commands/complete_fivec_project.py
hifive/commands/complete_hic_project.py
hifive/commands/connect_files.py
hifive/commands/create_fendset.py
hifive/commands/create_fivec_dataset.py
hifive/commands/create_fivec_heatmap.py
hifive/commands/create_fivec_project.py
hifive/commands/create_fragmentset.py
hifive/commands/create_hic_dataset.py
hifive/commands/create_hic_heatmap.py
hifive/commands/create_hic_mrheatmap.py
hifive/commands/create_hic_project.py
hifive/commands/find_quasar_scores.py
hifive/commands/get_fivec_interval.py
hifive/commands/get_hic_interval.py
hifive/commands/normalize_fivec_project.py
hifive/commands/normalize_hic_project.py
hifive/libraries/__init__.py
hifive/libraries/_fivec_binning.so
hifive/libraries/_fivec_optimize.so
hifive/libraries/_hic_binning.so
hifive/libraries/_hic_distance.so
hifive/libraries/_hic_domains.so
hifive/libraries/_hic_interactions.so
hifive/libraries/_hic_optimize.so
hifive/libraries/_hmm.so
hifive/libraries/_quasar.so
hifive/libraries/hmm.py
hifive-1.5.7.data/scripts/fetch_mrh_data
hifive-1.5.7.data/scripts/hifive
hifive-1.5.7.dist-info/LICENSE.txt
hifive-1.5.7.dist-info/METADATA
hifive-1.5.7.dist-info/WHEEL
hifive-1.5.7.dist-info/top_level.txt
hifive-1.5.7.dist-info/RECORD
