Metadata-Version: 2.1
Name: hifive
Version: 1.5.7
Summary: Python library for normalizing and analyzing HiC and 5C data
Home-page: https://github.com/bxlab/hifive
Author: Michael Sauria
Author-email: mike.sauria@jhu.edu
License: UNKNOWN
Download-URL: https://github.com/bxlab/hifive/tarball/1.5.7
Platform: UNKNOWN
Requires-Dist: numpy
Requires-Dist: scipy
Requires-Dist: h5py
